{
  "version": "0.3.3",
  "flags": {},
  "shapes": [
    {
      "label": "I",
      "text": "",
      "points": [
        [
          817.0,
          260.0
        ],
        [
          796.0,
          257.0
        ],
        [
          781.0,
          263.0
        ],
        [
          765.0,
          292.0
        ],
        [
          762.0,
          334.0
        ],
        [
          779.0,
          405.0
        ],
        [
          779.0,
          442.0
        ],
        [
          761.0,
          523.0
        ],
        [
          750.0,
          545.0
        ],
        [
          740.0,
          543.0
        ],
        [
          710.0,
          464.0
        ],
        [
          686.0,
          442.0
        ],
        [
          667.0,
          436.0
        ],
        [
          634.0,
          439.0
        ],
        [
          608.0,
          459.0
        ],
        [
          592.0,
          486.0
        ],
        [
          560.0,
          439.0
        ],
        [
          534.0,
          425.0
        ],
        [
          514.0,
          424.0
        ],
        [
          479.0,
          431.0
        ],
        [
          452.0,
          457.0
        ],
        [
          419.0,
          438.0
        ],
        [
          374.0,
          441.0
        ],
        [
          345.0,
          466.0
        ],
        [
          328.0,
          504.0
        ],
        [
          296.0,
          515.0
        ],
        [
          223.0,
          563.0
        ],
        [
          168.0,
          581.0
        ],
        [
          149.0,
          604.0
        ],
        [
          140.0,
          642.0
        ],
        [
          136.0,
          712.0
        ],
        [
          138.0,
          806.0
        ],
        [
          147.0,
          854.0
        ],
        [
          167.0,
          886.0
        ],
        [
          267.0,
          984.0
        ],
        [
          324.0,
          1067.0
        ],
        [
          340.0,
          1127.0
        ],
        [
          331.0,
          1194.0
        ],
        [
          310.0,
          1275.0
        ],
        [
          290.0,
          1290.0
        ],
        [
          282.0,
          1305.0
        ],
        [
          288.0,
          1342.0
        ],
        [
          204.0,
          1566.0
        ],
        [
          206.0,
          1595.0
        ],
        [
          742.0,
          1598.0
        ],
        [
          746.0,
          1593.0
        ],
        [
          749.0,
          1435.0
        ],
        [
          743.0,
          1409.0
        ],
        [
          779.0,
          1396.0
        ],
        [
          776.0,
          1382.0
        ],
        [
          753.0,
          1368.0
        ],
        [
          750.0,
          1358.0
        ],
        [
          760.0,
          1185.0
        ],
        [
          771.0,
          1123.0
        ],
        [
          824.0,
          961.0
        ],
        [
          843.0,
          875.0
        ],
        [
          851.0,
          787.0
        ],
        [
          849.0,
          635.0
        ],
        [
          876.0,
          459.0
        ],
        [
          870.0,
          349.0
        ],
        [
          849.0,
          297.0
        ]
      ],
      "group_id": null,
      "shape_type": "polygon",
      "flags": {}
    }
  ],
  "imagePath": "I_27.jpg",
  "imageData": null,
  "imageHeight": 1599,
  "imageWidth": 1200
}